import_gist/__init__.py
import_gist/core.py
import_gist-0.1.0.dist-info/METADATA
import_gist-0.1.0.dist-info/WHEEL
import_gist-0.1.0.dist-info/top_level.txt
import_gist-0.1.0.dist-info/RECORD
