Metadata-Version: 2.1
Name: import_gist
Version: 0.1.0
Summary: Import module from Github Gist
Home-page: https://github.com/alxxtexxr/import_gist
Author: alxxtexxr
Author-email: alimtegar404@gmail.com
Classifier: Programming Language :: Python :: 3
Classifier: License :: OSI Approved :: MIT License
Classifier: Operating System :: OS Independent
Requires-Python: >=3.6
Requires-Dist: requests
